bitbot-1.12.0.data/scripts/bitbotctl
bitbot-1.12.0.data/scripts/bitbotd
src/Cache.py
src/Config.py
src/Control.py
src/Database.py
src/EventManager.py
src/Exports.py
src/Hostmasks.py
src/IRCBot.py
src/IRCBuffer.py
src/IRCChannel.py
src/IRCChannels.py
src/IRCLine.py
src/IRCObject.py
src/IRCServer.py
src/IRCSocket.py
src/IRCUser.py
src/LockFile.py
src/Logging.py
src/ModuleManager.py
src/PollHook.py
src/PollSource.py
src/Socket.py
src/Timers.py
src/__init__.py
src/utils/__init__.py
src/utils/_consts_256_color.py
src/utils/cli.py
src/utils/consts.py
src/utils/http.py
src/utils/parse.py
src/utils/security.py
src/utils/irc/__init__.py
src/utils/irc/protocol.py
bitbot-1.12.0.dist-info/LICENSE
bitbot-1.12.0.dist-info/METADATA
bitbot-1.12.0.dist-info/WHEEL
bitbot-1.12.0.dist-info/top_level.txt
bitbot-1.12.0.dist-info/RECORD
