Metadata-Version: 2.1
Name: bitbot
Version: 1.12.0
Summary: Modular event-driven IRC bot
Home-page: https://github.com/jesopo/bitbot
Author: jesopo
Author-email: bitbot@jesopo.uk
License: UNKNOWN
Platform: linux
Classifier: Environment :: Console
Classifier: Environment :: No Input/Output (Daemon)
Classifier: Programming Language :: Python :: 3
Classifier: License :: OSI Approved :: GNU General Public License v2 (GPLv2)
Classifier: Operating System :: POSIX
Classifier: Topic :: Communications :: Chat :: Internet Relay Chat
Requires-Python: >=3.6
